{
  "main": {
    "name": "Luyando Chikandula",
    "occupation": "Fullstack web Developer && Software engineer @Shopeasy",
    "description": "Full Stack React Developer by Day, Founder && Freelancer by Night.",
    "image": "lu.jpg",
    "bio": "My name is Luyando, I'm a Full Stack web Developer. Currently I'm working at Shopeasy while studying Computer Science in college ",
    "contactmessage": "Get in touch with me to receive further details, get coached or anything else.",
    "email": "cluyando2@gmail.com",
    "phone": "+86 173 620 688 70",
    "address": {
      "street": "Independence Ave",
      "city": "Lusaka",
      "state": "Zambia",
      "zip": "10101"
    },
    "website": "http://www.timbakerdev.com",
    "resumedownload": "",
    "social": [
      {
        "name": "facebook",
        "url": "https://www.facebook.com/sonny.sangha.3",
        "className": "fa fa-facebook"
      },
      {
        "name": "linkedin",
        "url": "",
        "className": "fa fa-linkedin"
      },
      {
        "name": "instagram",
        "url": "",
        "className": "fa fa-instagram"
      },
      {
        "name": "github",
        "url": "",
        "className": "fa fa-github"
      }
    ]
  },
  "resume": {
    "skillmessage": "Here is some more details about my tech skills",
    "education": [
      {
        "school": "Weifanga University of Science And Technology",
        "degree": "BSc Computer Science and Technology",
        "graduated": "2018 - To-date",
        "description": "Studying a bachelor degree in computer science and technology"
      }
    ],
    "work": [
      {
        "company": "Shopeasy",
        "title": "Full stack web developer && Software engineer",
        "years": "February 2019 - Present",
        "description": "Developing e-commerce website"
      },
      {
        "company": "Ashers Masempela Music Ministry",
        "title": "Software Engineer and Digital marketing",
        "years": "August 2020 - Present",
        "description": "Developing online music store and digital marketing"
      }
    ],
    "skills": [
      {
        "name": "ReactJs",
        "level": "60%"
      },
      {
        "name": "CSS",
        "level": "95%"
      },
      {
        "name": "Git",
        "level": "90%"
      },
      {
        "name": "MySQL",
        "level": "75%"
      },
      {
        "name": "HTML5",
        "level": "98%"
      },
      {
        "name": "NodeJS",
        "level": "70%"
      }
    ]
  },
  "portfolio": {
    "projects": [
      {
        "title": "MERN Stack WhatsApp Clone",
        "category": "WhatsApp Clone built with MERN (MongoDB, ExpressJS, ReactJS, NodeJS)",
        "image": "whatsapp-mern.jpeg",
        "url": "https://www.youtube.com/watch?v=gzdQDxzW2Tw"
      },
      {
        "title": "MERN Stack TikTok Clone",
        "category": "TikTok Clone built with MERN (MongoDB, ExpressJS, ReactJS, NodeJS)",
        "image": "tiktok-mern.jpeg",
        "url": "https://www.youtube.com/watch?v=g8yGxDMyGiE"
      },
      {
        "title": "Facebook Clone with React",
        "category": "Facebook Clone built with ReactJS",
        "image": "facebook-clone.png",
        "url": "https://www.youtube.com/watch?v=B-kxUMHBxNo"
      },
      {
        "title": "Airbnb Clone",
        "category": "Facebook Clone built with ReactJS",
        "image": "airbnb-clone.jpeg",
        "url": "https://www.youtube.com/watch?v=BtJeH_-XYaA"
      },
      {
        "title": "Netflix Clone",
        "category": "Facebook Clone built with ReactJS",
        "image": "netflix-clone.jpeg",
        "url": "https://www.youtube.com/watch?v=XtMThy8QKqU&t=9358s"
      }
    ]
  },
  "testimonials": {
    "testimonials": [
      {
        "text": "I love the way you organize yourself and the way you are dedicated to your career",
        "user": "Majory"
      }
    ]
  }
}
